{
  "type": "slashblade:shaped_blade",
  "blade": "slashblade:yuzukitukumo",
  "category": "equipment",
  "key": {
    "B": {
      "fabric:type": "slashblade:blade",
      "type": "slashblade:blade",
      "item": "slashblade:slashblade",
      "request": {
        "enchantments": [
          {
            "id": "minecraft:fire_aspect"
          }
        ]
      }
    },
    "D": {
      "tag": "c:diamond_blocks"
    },
    "E": {
      "tag": "c:emerald_blocks"
    },
    "G": {
      "tag": "c:gold_blocks"
    },
    "I": {
      "tag": "c:iron_blocks"
    },
    "L": {
      "tag": "c:lapis_blocks"
    },
    "R": {
      "tag": "c:redstone_blocks"
    },
    "S": {
      "item": "slashblade:proudsoul_sphere"
    }
  },
  "pattern": [
    "ESD",
    "RBL",
    "ISG"
  ],
  "result": {
    "item": "slashblade:slashblade"
  },
  "show_notification": true
}